Metadata-Version: 2.2
Name: zeus-ml
Version: 0.11.0.post1
Summary: A framework for deep learning energy measurement and optimization.
Author: Zeus Team
License: Apache 2.0
Project-URL: Repository, https://github.com/ml-energy/zeus
Project-URL: Homepage, https://ml.energy/zeus
Project-URL: Documentation, https://ml.energy/zeus
Keywords: deep-learning,power,energy,carbon,sustainability,mlsys
Classifier: Environment :: GPU :: NVIDIA CUDA
Classifier: License :: OSI Approved :: Apache Software License
Classifier: Topic :: Scientific/Engineering :: Artificial Intelligence
Classifier: Programming Language :: Python :: 3.9
Classifier: Programming Language :: Python :: 3.10
Classifier: Programming Language :: Python :: 3.11
Classifier: Programming Language :: Python :: 3.12
Requires-Python: >=3.9
License-File: LICENSE
Requires-Dist: numpy
Requires-Dist: pandas
Requires-Dist: scikit-learn
Requires-Dist: nvidia-ml-py
Requires-Dist: pydantic
Requires-Dist: rich
Requires-Dist: tyro
Requires-Dist: httpx
Requires-Dist: amdsmi
Requires-Dist: python-dateutil
Provides-Extra: pfo
Requires-Dist: pydantic<2; extra == "pfo"
Provides-Extra: pfo-server
Requires-Dist: fastapi[standard]; extra == "pfo-server"
Requires-Dist: pydantic<2; extra == "pfo-server"
Requires-Dist: lowtime; extra == "pfo-server"
Requires-Dist: aiofiles; extra == "pfo-server"
Requires-Dist: torch; extra == "pfo-server"
Provides-Extra: bso
Requires-Dist: pydantic<2; extra == "bso"
Provides-Extra: bso-server
Requires-Dist: fastapi[standard]; extra == "bso-server"
Requires-Dist: sqlalchemy; extra == "bso-server"
Requires-Dist: pydantic<2; extra == "bso-server"
Requires-Dist: python-dotenv; extra == "bso-server"
Provides-Extra: migration
Requires-Dist: alembic; extra == "migration"
Requires-Dist: sqlalchemy; extra == "migration"
Requires-Dist: pydantic<2; extra == "migration"
Requires-Dist: python-dotenv; extra == "migration"
Provides-Extra: prometheus
Requires-Dist: prometheus-client; extra == "prometheus"
Provides-Extra: lint
Requires-Dist: ruff; extra == "lint"
Requires-Dist: black==22.6.0; extra == "lint"
Requires-Dist: pyright; extra == "lint"
Requires-Dist: pandas-stubs; extra == "lint"
Requires-Dist: transformers; extra == "lint"
Provides-Extra: test
Requires-Dist: fastapi[standard]; extra == "test"
Requires-Dist: sqlalchemy; extra == "test"
Requires-Dist: pydantic<2; extra == "test"
Requires-Dist: pytest==7.3.2; extra == "test"
Requires-Dist: pytest-mock==3.10.0; extra == "test"
Requires-Dist: pytest-xdist==3.3.1; extra == "test"
Requires-Dist: anyio==3.7.1; extra == "test"
Requires-Dist: aiosqlite==0.20.0; extra == "test"
Requires-Dist: numpy<2; extra == "test"
Provides-Extra: docs
Requires-Dist: mkdocs-material[imaging]==9.5.19; extra == "docs"
Requires-Dist: mkdocstrings[python]==0.25.0; extra == "docs"
Requires-Dist: mkdocs-gen-files==0.5.0; extra == "docs"
Requires-Dist: mkdocs-literate-nav==0.6.1; extra == "docs"
Requires-Dist: mkdocs-section-index==0.3.9; extra == "docs"
Requires-Dist: mkdocs-redirects==1.2.1; extra == "docs"
Requires-Dist: urllib3<2; extra == "docs"
Requires-Dist: black; extra == "docs"
Provides-Extra: dev
Requires-Dist: zeus-ml[bso,bso-server,lint,migration,pfo-server,prometheus,test]; extra == "dev"
Requires-Dist: greenlet; extra == "dev"
